CHANGES.txt
README.txt
bootstrap.py
setup.py
src/z3c/__init__.py
src/z3c.language.switch.egg-info/PKG-INFO
src/z3c.language.switch.egg-info/SOURCES.txt
src/z3c.language.switch.egg-info/dependency_links.txt
src/z3c.language.switch.egg-info/namespace_packages.txt
src/z3c.language.switch.egg-info/not-zip-safe
src/z3c.language.switch.egg-info/requires.txt
src/z3c.language.switch.egg-info/top_level.txt
src/z3c/language/__init__.py
src/z3c/language/switch/README.txt
src/z3c/language/switch/SETUP.cfg
src/z3c/language/switch/__init__.py
src/z3c/language/switch/adapters.py
src/z3c/language/switch/app.py
src/z3c/language/switch/configure.zcml
src/z3c/language/switch/interfaces.py
src/z3c/language/switch/property.py
src/z3c/language/switch/testing.py
src/z3c/language/switch/tests.py
src/z3c/language/switch/vocabulary.py
src/z3c/language/switch/z3c.language.switch-configure.zcml
src/z3c/language/switch/browser/__init__.py
src/z3c/language/switch/browser/configure.zcml
src/z3c/language/switch/browser/views.py
src/z3c/language/switch/generations/__init__.py
src/z3c/language/switch/generations/configure.zcml